z3c.currency-2.0-py3.9-nspkg.pth
z3c/currency/README.rst
z3c/currency/__init__.py
z3c/currency/configure.zcml
z3c/currency/converter.py
z3c/currency/field.py
z3c/currency/i18n.py
z3c/currency/interfaces.py
z3c/currency/tests.py
z3c.currency-2.0.dist-info/LICENSE.rst
z3c.currency-2.0.dist-info/METADATA
z3c.currency-2.0.dist-info/WHEEL
z3c.currency-2.0.dist-info/namespace_packages.txt
z3c.currency-2.0.dist-info/top_level.txt
z3c.currency-2.0.dist-info/RECORD
