Metadata-Version: 2.1
Name: z3c.currency
Version: 2.0
Summary: A currency field and support for ``z3c.form``.
Home-page: https://github.com/zopefoundation/z3c.currency
Author: Stephan Richter and the Zope Community
Author-email: zope-dev@zope.dev
License: ZPL 2.1
Keywords: zope3 currency schema field widget form
Classifier: Development Status :: 4 - Beta
Classifier: Environment :: Web Environment
Classifier: Intended Audience :: Developers
Classifier: License :: OSI Approved :: Zope Public License
Classifier: Programming Language :: Python
Classifier: Programming Language :: Python :: 3
Classifier: Programming Language :: Python :: 3.7
Classifier: Programming Language :: Python :: 3.8
Classifier: Programming Language :: Python :: 3.9
Classifier: Programming Language :: Python :: 3.10
Classifier: Programming Language :: Python :: 3.11
Classifier: Programming Language :: Python :: Implementation :: CPython
Classifier: Programming Language :: Python :: Implementation :: PyPy
Classifier: Natural Language :: English
Classifier: Operating System :: OS Independent
Classifier: Topic :: Internet :: WWW/HTTP
Classifier: Framework :: Zope :: 3
Requires-Python: >=3.7
License-File: LICENSE.rst
Requires-Dist: setuptools
Requires-Dist: zope.i18n
Requires-Dist: zope.i18nmessageid
Requires-Dist: zope.interface
Requires-Dist: zope.schema
Provides-Extra: form
Requires-Dist: z3c.form ; extra == 'form'
Provides-Extra: test
Requires-Dist: z3c.form ; extra == 'test'
Requires-Dist: zope.testing ; extra == 'test'
Requires-Dist: zope.testrunner ; extra == 'test'
